declatravaux/__init__.py
declatravaux/__main__.py
declatravaux/archives.py
declatravaux/configuration.py
declatravaux/images_rc.py
declatravaux/main_window.py
declatravaux/static/mail.html
declatravaux/transmission_process.py
declatravaux/ui/DeclaTravaux.pro
declatravaux/ui/DeclaTravaux.pro.user
declatravaux/ui/cancel.svg
declatravaux/ui/checked.svg
declatravaux/ui/images.qrc
declatravaux/ui/main.cpp
declatravaux/ui/main_window.cpp
declatravaux/ui/main_window.h
declatravaux/ui/main_window.ui
declatravaux/ui_main_window.py
declatravaux/workers.py
declatravaux-0.1.11.dist-info/LICENSE.txt
declatravaux-0.1.11.dist-info/WHEEL
declatravaux-0.1.11.dist-info/METADATA
declatravaux-0.1.11.dist-info/RECORD
